[
    {
        "dimensions": {
            "height": 1350,
            "width": 1080
        },
        "display_url": "https://instagram.fpoa4-1.fna.fbcdn.net/vp/254b41780a78f89cb6754e6a043c20a2/5B351042/t51.2885-15/e35/28751168_201958817241469_1158229255256014848_n.jpg",
        "edge_liked_by": {
            "count": 5229
        },
        "edge_media_to_caption": {
            "edges": [
                {
                    "node": {
                        "text": "Gooood morning!!.\n.\n.\nSalad for breakfast today! 💛\nTrying to beat the heat!\n.\nHope you guys are having a great weekend... 😊\n.\n.\n#vegan #veganfood#fruit #foodie#nutritarian#vegetarian#glutenfree#fruitplatter #salad #saladplatter #healthy #yum #eattherainbow #food"
                    }
                }
            ]
        },
        "edge_media_to_comment": {
            "count": 95
        },
        "id": "1737345115826323623",
        "is_video": false,
        "location": {
            "has_public_page": true,
            "id": "213011753",
            "name": "Sydney, Australia",
            "slug": "sydney-australia"
        },
        "owner": {
            "id": "22361768"
        },
        "shortcode": "BgcSi2RFoCn",
        "tags": [
            "eattherainbow",
            "foodie",
            "salad",
            "glutenfree",
            "healthy",
            "vegetarian",
            "veganfood",
            "food",
            "fruit",
            "yum",
            "vegan",
            "fruitplatter",
            "nutritarian",
            "saladplatter"
        ],
        "taken_at_timestamp": 1521327698,
        "thumbnail_src": "https://instagram.fpoa4-1.fna.fbcdn.net/vp/c2be974b8c379f07d2d5eb6ad8273275/5B292C90/t51.2885-15/s640x640/sh0.08/e35/c0.135.1080.1080/28751168_201958817241469_1158229255256014848_n.jpg",
        "urls": [
            "https://instagram.fpoa4-1.fna.fbcdn.net/t51.2885-15/e35/28751168_201958817241469_1158229255256014848_n.jpg"
        ]
    },
    {
        "dimensions": {
            "height": 640,
            "width": 640
        },
        "display_url": "https://instagram.fpoa4-1.fna.fbcdn.net/vp/457af82343a2c6cbd3e3bc08904e9cc3/5AB41251/t51.2885-15/e15/29088407_225909027973827_826848128660406272_n.jpg",
        "edge_liked_by": {
            "count": 828
        },
        "edge_media_to_caption": {
            "edges": [
                {
                    "node": {
                        "text": "Tag who you’d share this with 😈\n.\nFollow us (@paulbryantv) for more\n.\nBy @foodnetwork"
                    }
                }
            ]
        },
        "edge_media_to_comment": {
            "count": 15
        },
        "id": "1739590317487527715",
        "is_video": true,
        "location": {
            "has_public_page": true,
            "id": "212999109",
            "name": "Los Angeles, California",
            "slug": "los-angeles-california"
        },
        "owner": {
            "id": "3104192711"
        },
        "shortcode": "BgkRC1QjZcj",
        "tags": [],
        "taken_at_timestamp": 1521595378,
        "thumbnail_src": "https://instagram.fpoa4-1.fna.fbcdn.net/vp/457af82343a2c6cbd3e3bc08904e9cc3/5AB41251/t51.2885-15/e15/29088407_225909027973827_826848128660406272_n.jpg",
        "urls": [
            "https://instagram.fpoa4-1.fna.fbcdn.net/vp/ac64ba444a34c39e29379261e6a9b263/5AB410EA/t50.2886-16/29153713_1028325500653687_6555582452750876672_n.mp4"
        ],
        "video_view_count": 0
    }
]
